TFServingSpark-0.1.0.dist-info/DESCRIPTION.rst
TFServingSpark-0.1.0.dist-info/METADATA
TFServingSpark-0.1.0.dist-info/RECORD
TFServingSpark-0.1.0.dist-info/WHEEL
TFServingSpark-0.1.0.dist-info/metadata.json
TFServingSpark-0.1.0.dist-info/top_level.txt
tss/__init__.py
tss/save.py
tss/serving.py
